streamlit_gosling/__init__.py
streamlit_gosling/frontend/build/asset-manifest.json
streamlit_gosling/frontend/build/index.html
streamlit_gosling/frontend/build/static/css/main.76216b5a.css
streamlit_gosling/frontend/build/static/css/main.76216b5a.css.map
streamlit_gosling/frontend/build/static/js/161.df59ff7f.chunk.js
streamlit_gosling/frontend/build/static/js/161.df59ff7f.chunk.js.LICENSE.txt
streamlit_gosling/frontend/build/static/js/161.df59ff7f.chunk.js.map
streamlit_gosling/frontend/build/static/js/213.2ebe12a3.chunk.js
streamlit_gosling/frontend/build/static/js/213.2ebe12a3.chunk.js.LICENSE.txt
streamlit_gosling/frontend/build/static/js/213.2ebe12a3.chunk.js.map
streamlit_gosling/frontend/build/static/js/239.3883b350.chunk.js
streamlit_gosling/frontend/build/static/js/239.3883b350.chunk.js.LICENSE.txt
streamlit_gosling/frontend/build/static/js/239.3883b350.chunk.js.map
streamlit_gosling/frontend/build/static/js/732.da6e88e1.chunk.js
streamlit_gosling/frontend/build/static/js/732.da6e88e1.chunk.js.map
streamlit_gosling/frontend/build/static/js/main.98399f26.js
streamlit_gosling/frontend/build/static/js/main.98399f26.js.LICENSE.txt
streamlit_gosling/frontend/build/static/js/main.98399f26.js.map
streamlit_gosling-0.1.4.dist-info/LICENSE
streamlit_gosling-0.1.4.dist-info/METADATA
streamlit_gosling-0.1.4.dist-info/WHEEL
streamlit_gosling-0.1.4.dist-info/top_level.txt
streamlit_gosling-0.1.4.dist-info/RECORD
