Metadata-Version: 2.1
Name: streamlit-gosling
Version: 0.1.4
Summary: Gosling custom component for Streamlit
Home-page: https://github.com/gosling-lang/streamlit-gosling
Author: Qianwen Wang
Author-email: qianwen.april.wang@gmail.com
Requires-Python: >=3.9
License-File: LICENSE
Requires-Dist: streamlit >=1.20.0
Requires-Dist: gosling >=0.2.1
